cue/account.py
cue/arithmetic.py
cue/data.py
cue/invoice.py
cue/journal.py
cue/ledger.py
cue/cli/__main__.py
cue/cli/account.py
cue/cli/bin.py
cue/cli/invoice.py
cue/cli/ledger.py
cue/cli/templates/billing_address.txt
cue/cli/templates/date.txt
cue/cli/templates/header.txt
cue/cli/templates/invoice.txt
cue/cli/templates/items.txt
cue/cli/templates/settings.yml
cue/cli/templates/subtotal.txt
cue/cli/templates/tax_invoice.txt
cue/cli/templates/taxes.txt
cue/cli/templates/terms.txt
cue/cli/templates/title.txt
cue/cli/templates/token_spec.yml
cue/cli/templates/total.txt
tests/test_account.py
tests/test_cli.py
tests/test_journal.py
tests/test_ledger.py
tests/unit_test.py
cue-0.9.dist-info/LICENSE.txt
cue-0.9.dist-info/METADATA
cue-0.9.dist-info/WHEEL
cue-0.9.dist-info/entry_points.txt
cue-0.9.dist-info/top_level.txt
cue-0.9.dist-info/RECORD
