Metadata-Version: 2.1
Name: cue
Version: 0.9
Summary: Accounting system for linux
Home-page: https://kosciuszko.cloud
Author: Jonas McCallum
Author-email: jonasmccallum@gmail.com
License: UNKNOWN
Project-URL: Source, https://bitbucket.org/kosciuszko/cue
Project-URL: Tracker, https://bitbucket.org/kosciuszko/cue/issues
Platform: UNKNOWN
Requires-Dist: ruamel.yaml
Requires-Dist: wheezy.template
Provides-Extra: testing
Requires-Dist: pytest ; extra == 'testing'
